{
  "info_jugador": {
    "nombre": "Eika",
    "nombre_real": "Jérémy Valdenaire",
    "edad": 28,
    "equipo": "Gentle Mates",
    "pais": "France",
    "contrato_hasta": "2025-11-17T00:00:00.000Z",
    "redes_sociales": {
      "twitter": "https://twitter.com/Eikalol",
      "twitch": "https://twitch.tv/eikap"
    },
    "imagen_jugador": "https://dpm.lol/esport/players/eika.webp",
    "logo_equipo": "https://dpm.lol/esport/teams/M8.webp"
  },
  "cuentas": [
    {
      "nombre": "Jonathan Bailey#zzz",
      "nivel": 1084,
      "region": "EUW1",
      "liga": "GRANDMASTER I",
      "lp": 964,
      "victorias": 476,
      "derrotas": 432,
      "ultima_partida": 1753384198961
    }
  ],
  "campeones_recientes": [
    {
      "nombre": "Aurora",
      "partidas": 14,
      "victorias": 8,
      "winrate": "57.1%",
      "kda_promedio": 3.5
    },
    {
      "nombre": "Orianna",
      "partidas": 8,
      "victorias": 7,
      "winrate": "87.5%",
      "kda_promedio": 6.5
    },
    {
      "nombre": "Corki",
      "partidas": 6,
      "victorias": 4,
      "winrate": "66.7%",
      "kda_promedio": 2.289473684210526
    },
    {
      "nombre": "Annie",
      "partidas": 4,
      "victorias": 3,
      "winrate": "75.0%",
      "kda_promedio": 2.8666666666666667
    },
    {
      "nombre": "Azir",
      "partidas": 4,
      "victorias": 2,
      "winrate": "50.0%",
      "kda_promedio": 1.8333333333333333
    },
    {
      "nombre": "Syndra",
      "partidas": 4,
      "victorias": 3,
      "winrate": "75.0%",
      "kda_promedio": 3.6315789473684212
    },
    {
      "nombre": "Ryze",
      "partidas": 3,
      "victorias": 2,
      "winrate": "66.7%",
      "kda_promedio": 3.7857142857142856
    },
    {
      "nombre": "Taliyah",
      "partidas": 3,
      "victorias": 0,
      "winrate": "0.0%",
      "kda_promedio": 1.6470588235294117
    },
    {
      "nombre": "Ziggs",
      "partidas": 3,
      "victorias": 0,
      "winrate": "0.0%",
      "kda_promedio": 2.1333333333333333
    },
    {
      "nombre": "Ashe",
      "partidas": 2,
      "victorias": 0,
      "winrate": "0.0%",
      "kda_promedio": 1.3636363636363635
    }
  ],
  "estadisticas_2_semanas": {
    "games": 67,
    "wins": 36,
    "losses": 31,
    "timePlayed": 110924
  }
}