{
  "info_jugador": {
    "nombre": "escoX",
    "nombre_real": "Javier Escobedo Sevilla",
    "edad": 25,
    "equipo": "ZETA",
    "pais": "Spain",
    "contrato_hasta": "2025-11-17T00:00:00.000Z",
    "redes_sociales": {
      "twitter": "https://twitter.com/javieresco99",
      "twitch": "https://twitch.tv/escox_"
    },
    "imagen_jugador": "https://dpm.lol/esport/players/nopicture.webp",
    "logo_equipo": "https://dpm.lol/esport/teams/ZTA.webp"
  },
  "cuentas": [
    {
      "nombre": "Τadej Pogačar#Soria",
      "nivel": 1573,
      "region": "EUW1",
      "liga": "GRANDMASTER I",
      "lp": 946,
      "victorias": 298,
      "derrotas": 259,
      "ultima_partida": 1753470521902
    },
    {
      "nombre": "Keep Trying#Soria",
      "nivel": 189,
      "region": "EUW1",
      "liga": "MASTER I",
      "lp": 95,
      "victorias": 140,
      "derrotas": 108,
      "ultima_partida": 1753285360464
    }
  ],
  "campeones_recientes": [
    {
      "nombre": "Alistar",
      "partidas": 5,
      "victorias": 2,
      "winrate": "40.0%",
      "kda_promedio": 3.6470588235294117
    },
    {
      "nombre": "Bard",
      "partidas": 4,
      "victorias": 3,
      "winrate": "75.0%",
      "kda_promedio": 3.7857142857142856
    },
    {
      "nombre": "Rakan",
      "partidas": 4,
      "victorias": 2,
      "winrate": "50.0%",
      "kda_promedio": 3.230769230769231
    },
    {
      "nombre": "Rell",
      "partidas": 4,
      "victorias": 1,
      "winrate": "25.0%",
      "kda_promedio": 3.9166666666666665
    },
    {
      "nombre": "Galio",
      "partidas": 3,
      "victorias": 1,
      "winrate": "33.3%",
      "kda_promedio": 1.8571428571428572
    },
    {
      "nombre": "Nautilus",
      "partidas": 3,
      "victorias": 1,
      "winrate": "33.3%",
      "kda_promedio": 1.9642857142857142
    },
    {
      "nombre": "Poppy",
      "partidas": 3,
      "victorias": 1,
      "winrate": "33.3%",
      "kda_promedio": 1.52
    },
    {
      "nombre": "Braum",
      "partidas": 2,
      "victorias": 1,
      "winrate": "50.0%",
      "kda_promedio": 5.625
    },
    {
      "nombre": "Nami",
      "partidas": 2,
      "victorias": 1,
      "winrate": "50.0%",
      "kda_promedio": 3
    },
    {
      "nombre": "Neeko",
      "partidas": 2,
      "victorias": 1,
      "winrate": "50.0%",
      "kda_promedio": 2.9
    }
  ],
  "estadisticas_2_semanas": {
    "games": 43,
    "wins": 22,
    "losses": 21,
    "timePlayed": 69952
  }
}