{
  "info_jugador": {
    "nombre": "Only Spatula",
    "nombre_real": "",
    "edad": null,
    "equipo": null,
    "pais": null,
    "contrato_hasta": null,
    "redes_sociales": {
      "twitch": "https://twitch.tv/only_spatula_"
    },
    "imagen_jugador": "https://dpm.lol/esport/players/onlyspatula.webp",
    "logo_equipo": null
  },
  "cuentas": [
    {
      "nombre": "Peter Parkour#999",
      "nivel": 912,
      "region": "EUW1",
      "liga": "MASTER I",
      "lp": 42,
      "victorias": 269,
      "derrotas": 278,
      "ultima_partida": 1753730488458
    },
    {
      "nombre": "Only Spatula#999",
      "nivel": 312,
      "region": "EUW1",
      "liga": "CHALLENGER I",
      "lp": 1061,
      "victorias": 577,
      "derrotas": 526,
      "ultima_partida": 1753543959007
    },
    {
      "nombre": "Demon Fish#999",
      "nivel": 178,
      "region": "EUW1",
      "liga": "DIAMOND II",
      "lp": 75,
      "victorias": 358,
      "derrotas": 333,
      "ultima_partida": 1742683956246
    }
  ],
  "campeones_recientes": [
    {
      "nombre": "Hwei",
      "partidas": 33,
      "victorias": 20,
      "winrate": "60.6%",
      "kda_promedio": 2.9877300613496933
    },
    {
      "nombre": "Fizz",
      "partidas": 24,
      "victorias": 15,
      "winrate": "62.5%",
      "kda_promedio": 2.180451127819549
    },
    {
      "nombre": "Talon",
      "partidas": 15,
      "victorias": 5,
      "winrate": "33.3%",
      "kda_promedio": 1.6140350877192982
    },
    {
      "nombre": "Vex",
      "partidas": 7,
      "victorias": 2,
      "winrate": "28.6%",
      "kda_promedio": 1.8148148148148149
    },
    {
      "nombre": "Viego",
      "partidas": 6,
      "victorias": 3,
      "winrate": "50.0%",
      "kda_promedio": 2.0833333333333335
    },
    {
      "nombre": "Zilean",
      "partidas": 1,
      "victorias": 0,
      "winrate": "0.0%",
      "kda_promedio": 1.25
    }
  ],
  "estadisticas_2_semanas": {
    "games": 86,
    "wins": 45,
    "losses": 41,
    "timePlayed": 141201
  }
}