{
  "info_jugador": {
    "nombre": "Seal",
    "nombre_real": "Fabian de Lint",
    "edad": 24,
    "equipo": "Crvena zvezda Esports",
    "pais": "Netherlands",
    "contrato_hasta": null,
    "redes_sociales": {
      "twitter": "https://twitter.com/DealerSeal"
    },
    "imagen_jugador": "https://dpm.lol/esport/players/nopicture.webp",
    "logo_equipo": "https://dpm.lol/esport/teams/CZV.webp"
  },
  "cuentas": [
    {
      "nombre": "Spellbook Reader#book",
      "nivel": 161,
      "region": "EUW1",
      "liga": "CHALLENGER I",
      "lp": 1039,
      "victorias": 137,
      "derrotas": 96,
      "ultima_partida": 1753691626689
    },
    {
      "nombre": "Autumn Leaf#Seal",
      "nivel": 765,
      "region": "EUW1",
      "liga": "CHALLENGER I",
      "lp": 1426,
      "victorias": 203,
      "derrotas": 148,
      "ultima_partida": 1753522112127
    }
  ],
  "campeones_recientes": [
    {
      "nombre": "Neeko",
      "partidas": 2,
      "victorias": 2,
      "winrate": "100.0%",
      "kda_promedio": 2.7142857142857144
    },
    {
      "nombre": "Rakan",
      "partidas": 2,
      "victorias": 0,
      "winrate": "0.0%",
      "kda_promedio": 2.1538461538461537
    },
    {
      "nombre": "Elise",
      "partidas": 1,
      "victorias": 0,
      "winrate": "0.0%",
      "kda_promedio": 2.25
    },
    {
      "nombre": "Karma",
      "partidas": 1,
      "victorias": 1,
      "winrate": "100.0%",
      "kda_promedio": 3.5714285714285716
    },
    {
      "nombre": "Leona",
      "partidas": 1,
      "victorias": 1,
      "winrate": "100.0%",
      "kda_promedio": 2.2222222222222223
    }
  ],
  "estadisticas_2_semanas": {
    "games": 7,
    "wins": 4,
    "losses": 3,
    "timePlayed": 11990
  }
}