{
  "info_jugador": {
    "nombre": "Tommy",
    "nombre_real": "",
    "edad": null,
    "equipo": null,
    "pais": null,
    "contrato_hasta": null,
    "redes_sociales": {
      "twitter": "https://twitter.com/Tommy_XDXD",
      "twitch": "https://twitch.tv/tommyg33"
    },
    "imagen_jugador": "https://dpm.lol/esport/players/tommy.webp",
    "logo_equipo": null
  },
  "cuentas": [
    {
      "nombre": "LiL TommyG#EUW",
      "nivel": 1266,
      "region": "EUW1",
      "liga": "CHALLENGER I",
      "lp": 1264,
      "victorias": 415,
      "derrotas": 366,
      "ultima_partida": 1753005595520
    }
  ],
  "campeones_recientes": [
    {
      "nombre": "Bard",
      "partidas": 7,
      "victorias": 3,
      "winrate": "42.9%",
      "kda_promedio": 3.5555555555555554
    },
    {
      "nombre": "Rell",
      "partidas": 1,
      "victorias": 0,
      "winrate": "0.0%",
      "kda_promedio": 1
    }
  ],
  "estadisticas_2_semanas": {
    "games": 8,
    "wins": 3,
    "losses": 5,
    "timePlayed": 15272
  }
}